timeout_robotframework/__init__.py
timeout_robotframework/function_timeout.py
timeout_robotframework-1.0.0.dist-info/METADATA
timeout_robotframework-1.0.0.dist-info/WHEEL
timeout_robotframework-1.0.0.dist-info/top_level.txt
timeout_robotframework-1.0.0.dist-info/RECORD
