Metadata-Version: 2.1
Name: timeout-robotframework
Version: 1.0.0
Summary: Package to create timeout process robot framework
Author: Annas Wahyu Ramadhan
Classifier: Programming Language :: Python :: 3
Classifier: License :: OSI Approved :: MIT License
Classifier: Operating System :: OS Independent
Requires-Python: >=3.7
